examples/06_and_07/print_pcap_files/print_pcap_files.py
examples/07/download_map/download_map.py
examples/07/flood/flood.py
examples/07/gui_client/gui_client.py
examples/07/snap_printer/snap_printer.py
twnet_parser/__init__.py
twnet_parser/__version__.py
twnet_parser/chunk_header.py
twnet_parser/connless_message.py
twnet_parser/constants.py
twnet_parser/ctrl_message.py
twnet_parser/ddnet_uuid.py
twnet_parser/enum6.py
twnet_parser/enum7.py
twnet_parser/error.py
twnet_parser/huffman.py
twnet_parser/huffman_twnet_parser.py
twnet_parser/master_server.py
twnet_parser/message_parser.py
twnet_parser/msg6.py
twnet_parser/msg7.py
twnet_parser/net_message.py
twnet_parser/obj6.py
twnet_parser/obj7.py
twnet_parser/packer.py
twnet_parser/packet.py
twnet_parser/packet6.py
twnet_parser/packet7.py
twnet_parser/pretty_print.py
twnet_parser/serialize.py
twnet_parser/session.py
twnet_parser/session7.py
twnet_parser/snap_item.py
twnet_parser/snapshot.py
twnet_parser/snapshot_storage.py
twnet_parser/uuid_manager.py
twnet_parser/item_matcher/match_snap6.py
twnet_parser/item_matcher/match_snap7.py
twnet_parser/messages6/connless/count.py
twnet_parser/messages6/connless/forward_check.py
twnet_parser/messages6/connless/forward_error.py
twnet_parser/messages6/connless/forward_ok.py
twnet_parser/messages6/connless/forward_response.py
twnet_parser/messages6/connless/heartbeat.py
twnet_parser/messages6/connless/info.py
twnet_parser/messages6/connless/list.py
twnet_parser/messages6/connless/request_count.py
twnet_parser/messages6/connless/request_info.py
twnet_parser/messages6/connless/request_list.py
twnet_parser/messages6/control/accept_connect.py
twnet_parser/messages6/control/ack_accept_connect.py
twnet_parser/messages6/control/close.py
twnet_parser/messages6/control/connect.py
twnet_parser/messages6/control/keep_alive.py
twnet_parser/messages6/control/token.py
twnet_parser/messages6/game/cl_call_vote.py
twnet_parser/messages6/game/cl_change_info.py
twnet_parser-0.15.1.dist-info/licenses/LICENSE.txt
twnet_parser-0.15.1.dist-info/METADATA
twnet_parser-0.15.1.dist-info/WHEEL
twnet_parser-0.15.1.dist-info/top_level.txt
twnet_parser-0.15.1.dist-info/RECORD
