Metadata-Version: 2.4
Name: twnet_parser
Version: 0.15.1
Summary: A teeworlds network protocol library, designed according to sans I/O (http://sans-io.readthedocs.io/) principles
Home-page: https://gitlab.com/teeworlds-network/twnet_parser
Author: ChillerDragon
Author-email: chillerdragon@gmail.com
License: BSD-2.0
Project-URL: Bug Tracker, https://gitlab.com/teeworlds-network/twnet_parser/-/issues
Project-URL: repository, https://gitlab.com/teeworlds-network/twnet_parser
Classifier: Development Status :: 3 - Alpha
Classifier: Programming Language :: Python :: 3
Classifier: License :: OSI Approved :: BSD License
Classifier: Operating System :: OS Independent
License-File: LICENSE.txt
Dynamic: license-file
